CHANGES.txt
LICENSE.txt
MANIFEST.in
README.txt
setup.py
js/__init__.py
js.obviel.egg-info/PKG-INFO
js.obviel.egg-info/SOURCES.txt
js.obviel.egg-info/dependency_links.txt
js.obviel.egg-info/entry_points.txt
js.obviel.egg-info/namespace_packages.txt
js.obviel.egg-info/not-zip-safe
js.obviel.egg-info/requires.txt
js.obviel.egg-info/top_level.txt
js/obviel/__init__.py
js/obviel/resources/json-template.js
js/obviel/resources/json2.js
js/obviel/resources/obviel-datatables.js
js/obviel/resources/obviel-forms-autocomplete.js
js/obviel/resources/obviel-forms-datepicker.js
js/obviel/resources/obviel-forms-nl.js
js/obviel/resources/obviel-forms-ui.js
js/obviel/resources/obviel-forms.js
js/obviel/resources/obviel-jgrowl.js
js/obviel/resources/obviel-patterns.js
js/obviel/resources/obviel.js