Metadata-Version: 1.0
Name: js.obviel
Version: 0.11.1
Summary: Fanstatic packaging of Obviel
Home-page: UNKNOWN
Author: Fanstatic Developers
Author-email: fanstatic@googlegroups.com
License: BSD
Platform: UNKNOWN
